pactman-stubs/__init__.pyi
pactman-stubs/__main__.pyi
pactman-stubs/__version__.pyi
pactman-stubs/mock/__init__.pyi
pactman-stubs/mock/consumer.pyi
pactman-stubs/mock/mock_urlopen.pyi
pactman-stubs/mock/pact.pyi
pactman-stubs/mock/pact_request_handler.pyi
pactman-stubs/py.typed
pactman-stubs/verifier/result.pyi
pactman-stubs/verifier/verify.pyi
requests-stubs/models.pyi
requests-stubs/py.typed
requests-stubs/types.pyi
starlette-stubs/__init__.pyi
starlette-stubs/py.typed
starlette-stubs/testclient.pyi
outcome_stubs-0.5.5.dist-info/WHEEL
outcome_stubs-0.5.5.dist-info/METADATA
outcome_stubs-0.5.5.dist-info/RECORD
